hueniverse/__init__.py
hueniverse/async.py
hueniverse-0.1.0.dist-info/METADATA
hueniverse-0.1.0.dist-info/WHEEL
hueniverse-0.1.0.dist-info/RECORD
